{
  "project_info": {
    "project_number": "461042932123",
    "project_id": "help2go-c6de9",
    "storage_bucket": "help2go-c6de9.appspot.com"
  },
  "client": [
    {
      "client_info": {
        "mobilesdk_app_id": "1:461042932123:android:43967b4155f87c9b66693e",
        "android_client_info": {
          "package_name": "com.help2go"
        }
      },
      "oauth_client": [
        {
          "client_id": "461042932123-si1k0u3n2lrveaifnot6a7chhkn3rl92.apps.googleusercontent.com",
          "client_type": 3
        }
      ],
      "api_key": [
        {
          "current_key": "AIzaSyBtL3xTZ4ytNJG85zqnjkaD3TIzkYsqKqU"
        }
      ],
      "services": {
        "appinvite_service": {
          "other_platform_oauth_client": [
            {
              "client_id": "461042932123-si1k0u3n2lrveaifnot6a7chhkn3rl92.apps.googleusercontent.com",
              "client_type": 3
            }
          ]
        }
      }
    }
  ],
  "configuration_version": "1"
}